ensue_cli/__init__.py
ensue_cli/cli.py
ensue_cli/client.py
ensue_cli-0.1.2.dist-info/METADATA
ensue_cli-0.1.2.dist-info/WHEEL
ensue_cli-0.1.2.dist-info/entry_points.txt
ensue_cli-0.1.2.dist-info/RECORD
