Metadata-Version: 2.4
Name: ensue-cli
Version: 0.1.2
Summary: CLI for Ensue Memory - a distributed memory network for AI agents built on MCP, enabling persistent, shared context across conversations and applications
Project-URL: Homepage, https://www.ensue-network.ai
Project-URL: Repository, https://github.com/mutable-state-inc/ensue-cli
Project-URL: Documentation, https://www.ensue-network.ai/docs
Author: Mutable State Inc
Keywords: agents,ai,cli,ensue,mcp,memory,model-context-protocol
Classifier: Development Status :: 4 - Beta
Classifier: Environment :: Console
Classifier: Intended Audience :: Developers
Classifier: Operating System :: OS Independent
Classifier: Programming Language :: Python :: 3
Classifier: Programming Language :: Python :: 3.9
Classifier: Programming Language :: Python :: 3.10
Classifier: Programming Language :: Python :: 3.11
Classifier: Programming Language :: Python :: 3.12
Classifier: Topic :: Software Development :: Libraries :: Python Modules
Requires-Python: >=3.9
Requires-Dist: click>=8.0
Requires-Dist: mcp>=1.0
Requires-Dist: rich>=13.0
Provides-Extra: dev
Requires-Dist: build>=1.0; extra == 'dev'
Requires-Dist: pytest-asyncio>=0.21; extra == 'dev'
Requires-Dist: pytest-cov>=4.0; extra == 'dev'
Requires-Dist: pytest>=7.0; extra == 'dev'
Requires-Dist: ruff>=0.8; extra == 'dev'
Requires-Dist: twine>=4.0; extra == 'dev'
